linestuffup/__init__.py
linestuffup/_graph_copy_for_zarr.py
linestuffup/_version.py
linestuffup/base.py
linestuffup/graph.py
linestuffup/gui.py
linestuffup/ndarray_shifted.py
linestuffup/utils.py
linestuffup/webmzarr.py
LineStuffUp-0.1.0.dist-info/LICENSE.txt
LineStuffUp-0.1.0.dist-info/METADATA
LineStuffUp-0.1.0.dist-info/WHEEL
LineStuffUp-0.1.0.dist-info/top_level.txt
LineStuffUp-0.1.0.dist-info/RECORD
