Metadata-Version: 2.1
Name: LineStuffUp
Version: 0.1.0
Summary: 3D nonlinear alignment for microscopy and neuroimaging
Home-page: https://github.com/mwshinn/LineStuffUp
Author: Max Shinn
Author-email: m.shinn@ucl.ac.uk
Maintainer: Max Shinn
Maintainer-email: m.shinn@ucl.ac.uk
License: MIT
Classifier: Topic :: Scientific/Engineering
Classifier: Topic :: Scientific/Engineering :: Bio-Informatics
Classifier: Topic :: Scientific/Engineering :: Visualization
Classifier: Topic :: Multimedia :: Graphics
Classifier: Programming Language :: Python :: 3
Classifier: License :: OSI Approved :: MIT License
Classifier: Development Status :: 4 - Beta
Requires-Python: >=3.7
License-File: LICENSE.txt
Requires-Dist: numpy
Requires-Dist: scipy
Requires-Dist: napari
Requires-Dist: magicgui
Requires-Dist: scikit-image
Requires-Dist: imageio
Requires-Dist: imageio-ffmpeg
